qrcodegen.py
qrcodegen-1.8.0.dist-info/METADATA
qrcodegen-1.8.0.dist-info/WHEEL
qrcodegen-1.8.0.dist-info/top_level.txt
qrcodegen-1.8.0.dist-info/RECORD
