Metadata-Version: 1.2
Name: qrcodegen
Version: 1.8.0
Summary: High quality QR Code generator library for Python
Home-page: https://www.nayuki.io/page/qr-code-generator-library
Author: Project Nayuki
Author-email: me@nayuki.io
License: MIT License
Platform: OS Independent
Classifier: Development Status :: 5 - Production/Stable
Classifier: Intended Audience :: Developers
Classifier: Intended Audience :: Information Technology
Classifier: License :: OSI Approved :: MIT License
Classifier: Operating System :: OS Independent
Classifier: Programming Language :: Python
Classifier: Programming Language :: Python :: 3
Classifier: Topic :: Multimedia :: Graphics
Classifier: Topic :: Software Development :: Libraries :: Python Modules
Requires-Python: >=3
